xonsh_jupyter/__init__.py
xonsh_jupyter/alias.py
xonsh_jupyter/kernel.py
xonsh_jupyter/shell.py
xontrib/jupyter.py
xontrib_jupyter_shell-0.1.0.dist-info/LICENSE
xontrib_jupyter_shell-0.1.0.dist-info/METADATA
xontrib_jupyter_shell-0.1.0.dist-info/WHEEL
xontrib_jupyter_shell-0.1.0.dist-info/RECORD
