Metadata-Version: 2.1
Name: xontrib-jupyter-shell
Version: 0.1.0
Summary: A shell for the Jupyter kernel.
Home-page: https://github.com/xonsh/xontrib-jupyter-shell
License: MIT
Keywords: xontrib,xonsh
Author: Xonsh Dev
Author-email: jnoortheen@gmail.com
Requires-Python: >=3.7
Classifier: Intended Audience :: Developers
Classifier: License :: OSI Approved :: MIT License
Classifier: Natural Language :: English
Classifier: Operating System :: OS Independent
Classifier: Programming Language :: Python
Classifier: Programming Language :: Python :: 3
Classifier: Programming Language :: Python :: 3.7
Classifier: Programming Language :: Python :: 3.8
Classifier: Programming Language :: Python :: 3.9
Classifier: Programming Language :: Python :: 3.10
Classifier: Programming Language :: Python :: 3.11
Classifier: Programming Language :: Python :: 3
Classifier: Programming Language :: Python :: 3.6
Classifier: Programming Language :: Python :: 3.7
Classifier: Programming Language :: Python :: 3.8
Classifier: Topic :: System :: Shells
Classifier: Topic :: System :: System Shells
Classifier: Topic :: Terminals
Requires-Dist: jupyter (>=1.0.0,<2.0.0)
Requires-Dist: xonsh (>=0.12)
Project-URL: Code, https://github.com/xonsh/xontrib-jupyter-shell
Project-URL: Documentation, https://github.com/xonsh/xontrib-jupyter-shell/blob/master/README.md
Project-URL: Issue tracker, https://github.com/xonsh/xontrib-jupyter-shell/issues
Project-URL: Repository, https://github.com/xonsh/xontrib-jupyter-shell
